<annotation>
	<folder>金具</folder>
	<filename>06640.jpg</filename>
	<path>/home/data/all/06640.jpg</path>
	<source>
		<database>Unknown</database>
	</source>
	<size>
		<width>1840</width>
		<height>1228</height>
		<depth>3</depth>
	</size>
	<segmented>0</segmented>
	<object>
		<name>05020403</name>
		<pose>Unspecified</pose>
		<truncated>0</truncated>
		<difficult>0</difficult>
		<bndbox>
			<xmin>785</xmin>
			<ymin>599</ymin>
			<xmax>940</xmax>
			<ymax>674</ymax>
		</bndbox>
	</object>
	<object>
		<name>02010104</name>
		<pose>Unspecified</pose>
		<truncated>0</truncated>
		<difficult>0</difficult>
		<bndbox>
			<xmin>1006</xmin>
			<ymin>746</ymin>
			<xmax>1114</xmax>
			<ymax>835</ymax>
		</bndbox>
	</object>
</annotation>
