<annotation>
	<folder>金具</folder>
	<filename>06713.jpg</filename>
	<path>/home/data/all/06713.jpg</path>
	<source>
		<database>Unknown</database>
	</source>
	<size>
		<width>1840</width>
		<height>1228</height>
		<depth>3</depth>
	</size>
	<segmented>0</segmented>
	<object>
		<name>04010121</name>
		<pose>Unspecified</pose>
		<truncated>0</truncated>
		<difficult>0</difficult>
		<bndbox>
			<xmin>479</xmin>
			<ymin>403</ymin>
			<xmax>596</xmax>
			<ymax>468</ymax>
		</bndbox>
	</object>
	<object>
		<name>05020403</name>
		<pose>Unspecified</pose>
		<truncated>0</truncated>
		<difficult>0</difficult>
		<bndbox>
			<xmin>865</xmin>
			<ymin>455</ymin>
			<xmax>1005</xmax>
			<ymax>584</ymax>
		</bndbox>
	</object>
	<object>
		<name>05020403</name>
		<pose>Unspecified</pose>
		<truncated>0</truncated>
		<difficult>0</difficult>
		<bndbox>
			<xmin>496</xmin>
			<ymin>476</ymin>
			<xmax>599</xmax>
			<ymax>532</ymax>
		</bndbox>
	</object>
</annotation>
