<annotation>
	<folder>金具</folder>
	<filename>06725.jpg</filename>
	<path>/home/data/all/06725.jpg</path>
	<source>
		<database>Unknown</database>
	</source>
	<size>
		<width>1840</width>
		<height>1228</height>
		<depth>3</depth>
	</size>
	<segmented>0</segmented>
	<object>
		<name>05020403</name>
		<pose>Unspecified</pose>
		<truncated>0</truncated>
		<difficult>0</difficult>
		<bndbox>
			<xmin>892</xmin>
			<ymin>506</ymin>
			<xmax>1024</xmax>
			<ymax>742</ymax>
		</bndbox>
	</object>
	<object>
		<name>05020404</name>
		<pose>Unspecified</pose>
		<truncated>0</truncated>
		<difficult>0</difficult>
		<bndbox>
			<xmin>594</xmin>
			<ymin>468</ymin>
			<xmax>682</xmax>
			<ymax>561</ymax>
		</bndbox>
	</object>
	<object>
		<name>05020404</name>
		<pose>Unspecified</pose>
		<truncated>0</truncated>
		<difficult>0</difficult>
		<bndbox>
			<xmin>554</xmin>
			<ymin>635</ymin>
			<xmax>696</xmax>
			<ymax>799</ymax>
		</bndbox>
	</object>
	<object>
		<name>05020404</name>
		<pose>Unspecified</pose>
		<truncated>0</truncated>
		<difficult>0</difficult>
		<bndbox>
			<xmin>1210</xmin>
			<ymin>627</ymin>
			<xmax>1352</xmax>
			<ymax>791</ymax>
		</bndbox>
	</object>
</annotation>
